{"version":3,"kind":"Article","sha256":"4efb85050bec622664c8cf8ef85841f02fca1cf542885dd849fb3ea892404832","slug":"container-registry","location":"/applications/container_registry.md","dependencies":[],"frontmatter":{"title":"Container Registry","content_includes_title":false,"github":"https://github.com/eoxhub-workspaces/documentation","numbering":{"title":{"offset":1}},"source_url":"https://github.com/eoxhub-workspaces/documentation/blob/main/applications/container_registry.md","edit_url":"https://github.com/eoxhub-workspaces/documentation/edit/main/applications/container_registry.md","thumbnail":"/pr-preview/pr-34/build/registry-credentials-02f25ce12c1df7322c76cee8299e30ee.png","exports":[{"format":"md","filename":"container_registry.md","url":"/pr-preview/pr-34/build/container_registry-81c98a6ad94f21179241a6fbeec96f35.md"}]},"mdast":{"type":"root","children":[{"type":"block","children":[{"type":"heading","depth":2,"position":{"start":{"line":3,"column":1},"end":{"line":3,"column":1}},"children":[{"type":"text","value":"Login in UI","position":{"start":{"line":3,"column":1},"end":{"line":3,"column":1}},"key":"MSdPyGaAk1"}],"identifier":"login-in-ui","label":"Login in UI","html_id":"login-in-ui","implicit":true,"key":"sYFcxNLmFN"},{"type":"paragraph","position":{"start":{"line":5,"column":1},"end":{"line":5,"column":1}},"children":[{"type":"text","value":"The credentials can be found in the secret ","position":{"start":{"line":5,"column":1},"end":{"line":5,"column":1}},"key":"iMJ2jdvv9Q"},{"type":"strong","position":{"start":{"line":5,"column":1},"end":{"line":5,"column":1}},"children":[{"type":"text","value":"registry-login","position":{"start":{"line":5,"column":1},"end":{"line":5,"column":1}},"key":"oonbFSD9Ex"}],"key":"JzdRhHgLio"},{"type":"text","value":" in the ","position":{"start":{"line":5,"column":1},"end":{"line":5,"column":1}},"key":"y8eehMMCb0"},{"type":"link","url":"/secret-manager","position":{"start":{"line":5,"column":1},"end":{"line":5,"column":1}},"children":[{"type":"text","value":"credentials manager","position":{"start":{"line":5,"column":1},"end":{"line":5,"column":1}},"key":"drql5ij2Wa"}],"urlSource":"./secret_manager.md","dataUrl":"/secret-manager.json","internal":true,"protocol":"file","key":"n7QdLVpWNW"},{"type":"text","value":" or your workspace.","position":{"start":{"line":5,"column":1},"end":{"line":5,"column":1}},"key":"Kw6iRI4qIr"}],"key":"MB6sFeFKwF"},{"type":"container","kind":"figure","children":[{"type":"image","url":"/pr-preview/pr-34/build/registry-credentials-02f25ce12c1df7322c76cee8299e30ee.png","alt":"Credentials ‘registry-login’ contains the login information for the container registry.","data":{"altTextIsAutoGenerated":true},"key":"FxxXJrpagY","urlSource":"assets/credentials-manager/registry-credentials.png"},{"type":"caption","children":[{"type":"paragraph","position":{"start":{"line":11,"column":1},"end":{"line":11,"column":1}},"children":[{"type":"captionNumber","kind":"figure","label":"registry-credentials","identifier":"registry-credentials","html_id":"registry-credentials","enumerator":"1","children":[{"type":"text","value":"Figure ","key":"Civ3ih6vYh"},{"type":"text","value":"1","key":"MkXhOmotqA"},{"type":"text","value":":","key":"OuHghUpb6d"}],"template":"Figure %s:","key":"LUkshZz7IA"},{"type":"text","value":"Credentials ‘registry-login’ contains the login information for the container registry.","position":{"start":{"line":11,"column":1},"end":{"line":11,"column":1}},"key":"vKXjt5GGfJ"}],"key":"AMJkf6kckK"}],"key":"qkUFXPlRug"}],"label":"registry-credentials","identifier":"registry-credentials","enumerator":"1","html_id":"registry-credentials","key":"w4VaFdEh2h"},{"type":"container","kind":"figure","children":[{"type":"image","url":"/pr-preview/pr-34/build/registry-credentials-468c1c3d80a31d04a92a851a1f7973f5.png","alt":"Registry server FQDN (URL), Username & Password","data":{"altTextIsAutoGenerated":true},"key":"GceVqrSh5h","urlSource":"assets/credentials-manager/registry-credentials-detail.png"},{"type":"caption","children":[{"type":"paragraph","position":{"start":{"line":18,"column":1},"end":{"line":18,"column":1}},"children":[{"type":"captionNumber","kind":"figure","label":"registry-credentials-detail","identifier":"registry-credentials-detail","html_id":"registry-credentials-detail","enumerator":"2","children":[{"type":"text","value":"Figure ","key":"fUFYbtcHbI"},{"type":"text","value":"2","key":"DGm3JAKOmA"},{"type":"text","value":":","key":"H5xvv7GStE"}],"template":"Figure %s:","key":"FELunfe2VI"},{"type":"text","value":"Registry server FQDN (URL), Username & Password","position":{"start":{"line":18,"column":1},"end":{"line":18,"column":1}},"key":"pPbSIm6O7M"}],"key":"JLlxVbtCG3"}],"key":"aCGp6WxAci"}],"label":"registry-credentials-detail","identifier":"registry-credentials-detail","enumerator":"2","html_id":"registry-credentials-detail","key":"bvc24UULQj"},{"type":"heading","depth":2,"position":{"start":{"line":21,"column":1},"end":{"line":21,"column":1}},"children":[{"type":"text","value":"Upload images to registry","position":{"start":{"line":21,"column":1},"end":{"line":21,"column":1}},"key":"EcB1BHcpHO"}],"identifier":"upload-images-to-registry","label":"Upload images to registry","html_id":"upload-images-to-registry","implicit":true,"key":"AtauRHx8dT"},{"type":"list","ordered":true,"start":1,"spread":false,"position":{"start":{"line":23,"column":1},"end":{"line":39,"column":1}},"children":[{"type":"listItem","spread":true,"position":{"start":{"line":23,"column":1},"end":{"line":28,"column":1}},"children":[{"type":"paragraph","position":{"start":{"line":23,"column":1},"end":{"line":23,"column":1}},"children":[{"type":"text","value":"Login","position":{"start":{"line":23,"column":1},"end":{"line":23,"column":1}},"key":"FSvoHZfzXh"}],"key":"sjmzfjJh7W"},{"type":"code","lang":"shell","value":"docker login -u <username> registry.[workspace-name].[cluster].eox.at  # e.g. registry.hub-test-ws1.hub-test.eox.at","position":{"start":{"line":24,"column":1},"end":{"line":26,"column":1}},"key":"XYznkMtz1I"},{"type":"paragraph","position":{"start":{"line":27,"column":1},"end":{"line":27,"column":1}},"children":[{"type":"text","value":"Type in the password when asked.","position":{"start":{"line":27,"column":1},"end":{"line":27,"column":1}},"key":"GTKA2yVuZb"}],"key":"JfaN7pFv5L"}],"key":"z7nlafCB0w"},{"type":"listItem","spread":true,"position":{"start":{"line":29,"column":1},"end":{"line":33,"column":1}},"children":[{"type":"paragraph","position":{"start":{"line":29,"column":1},"end":{"line":29,"column":1}},"children":[{"type":"text","value":"Tag your image","position":{"start":{"line":29,"column":1},"end":{"line":29,"column":1}},"key":"ilxbf5BP6q"}],"key":"k5LgGjbn8a"},{"type":"code","lang":"shell","value":"docker tag my-image:latest registry.[workspace-name].[cluster].eox.at/my-image:latest","position":{"start":{"line":30,"column":1},"end":{"line":32,"column":1}},"key":"Sa2rMcD1mC"}],"key":"Wv5O9OfYcF"},{"type":"listItem","spread":true,"position":{"start":{"line":34,"column":1},"end":{"line":39,"column":1}},"children":[{"type":"paragraph","position":{"start":{"line":34,"column":1},"end":{"line":34,"column":1}},"children":[{"type":"text","value":"Push image to registry","position":{"start":{"line":34,"column":1},"end":{"line":34,"column":1}},"key":"K8R7QR6Sff"}],"key":"qVj4BOwXVr"},{"type":"code","lang":"shell","value":"docker push registry.[workspace-name].[cluster].eox.at/my-image:latest","position":{"start":{"line":36,"column":1},"end":{"line":38,"column":1}},"key":"n7SZtE72on"}],"key":"orM8N9sAqG"}],"key":"N3EfjTcoPl"},{"type":"paragraph","position":{"start":{"line":40,"column":1},"end":{"line":40,"column":1}},"children":[{"type":"text","value":"After a successful upload, the image is visible in the UI and in the file browser, and can be used in Argo Workflows, etc.","position":{"start":{"line":40,"column":1},"end":{"line":40,"column":1}},"key":"VKYCwkfTPK"}],"key":"JUzzKW7wOY"}],"key":"S7gMWcaAi9"}],"key":"pyI3T36u8N"},"references":{"cite":{"order":[],"data":{}}},"footer":{"navigation":{"prev":{"title":"eoAPI","url":"/eoapi","group":"Applications"},"next":{"title":"How to create an account in EOxHub workspaces","url":"/creating-account","group":"Tutorials"}}},"domain":"http://localhost:3000"}