{"version":3,"kind":"Article","sha256":"8201f70eb63a1d649eef4bcf3bbcdc69c9e8ecc3057d1e12faf7ba552f304992","slug":"getting-started","location":"/introduction/2_getting_started.md","dependencies":[],"frontmatter":{"title":"Getting Started with EOxHub Workspaces","content_includes_title":false,"github":"https://github.com/eoxhub-workspaces/documentation","numbering":{"title":{"offset":1}},"source_url":"https://github.com/eoxhub-workspaces/documentation/blob/main/introduction/2_getting_started.md","edit_url":"https://github.com/eoxhub-workspaces/documentation/edit/main/introduction/2_getting_started.md","thumbnail":"https://documentation.hub.eox.at//build/user_area-37d54bdce89943d00406bb03d1dfc070.png","exports":[{"format":"md","filename":"2_getting_started.md","url":"https://documentation.hub.eox.at//build/2_getting_started-b4fba24cae54a1b0f532e0cc351d3bbb.md"}]},"mdast":{"type":"root","children":[{"type":"block","children":[{"type":"paragraph","position":{"start":{"line":3,"column":1},"end":{"line":3,"column":1}},"children":[{"type":"text","value":"Welcome! This guide will walk you through the basic steps to start using ","position":{"start":{"line":3,"column":1},"end":{"line":3,"column":1}},"key":"wtM1aXX08M"},{"type":"strong","position":{"start":{"line":3,"column":1},"end":{"line":3,"column":1}},"children":[{"type":"text","value":"EOxHub Workspaces","position":{"start":{"line":3,"column":1},"end":{"line":3,"column":1}},"key":"c2K2RgYdRz"}],"key":"lwiP2NsF58"},{"type":"text","value":".","position":{"start":{"line":3,"column":1},"end":{"line":3,"column":1}},"key":"r3wjMblXs9"}],"key":"cGn8vewx7v"},{"type":"thematicBreak","position":{"start":{"line":5,"column":1},"end":{"line":5,"column":1}},"key":"W8ObUthw6w"},{"type":"heading","depth":2,"position":{"start":{"line":7,"column":1},"end":{"line":7,"column":1}},"children":[{"type":"text","value":"Sign Up","position":{"start":{"line":7,"column":1},"end":{"line":7,"column":1}},"key":"lJEL8GnysP"}],"identifier":"sign-up","label":"Sign Up","html_id":"sign-up","implicit":true,"key":"WhOLUqS99s"},{"type":"paragraph","position":{"start":{"line":9,"column":1},"end":{"line":9,"column":1}},"children":[{"type":"text","value":"To use EOxHub Workspaces, all you need is an Internet browser.","position":{"start":{"line":9,"column":1},"end":{"line":9,"column":1}},"key":"PCK5L3SXdL"}],"key":"E9oBJ3rwk4"},{"type":"list","ordered":true,"start":1,"spread":false,"position":{"start":{"line":11,"column":1},"end":{"line":16,"column":1}},"children":[{"type":"listItem","spread":true,"position":{"start":{"line":11,"column":1},"end":{"line":11,"column":1}},"children":[{"type":"paragraph","children":[{"type":"text","value":"Go to ","position":{"start":{"line":11,"column":1},"end":{"line":11,"column":1}},"key":"RtcFJT6XG2"},{"type":"link","url":"https://hub.eox.at","position":{"start":{"line":11,"column":1},"end":{"line":11,"column":1}},"children":[{"type":"text","value":"hub.eox.at","position":{"start":{"line":11,"column":1},"end":{"line":11,"column":1}},"key":"Ypz7f0jArA"}],"urlSource":"https://hub.eox.at","key":"sJvEv6DeME"},{"type":"text","value":" or navigate to the URL of your workspace","position":{"start":{"line":11,"column":1},"end":{"line":11,"column":1}},"key":"Lmsw4HSjpQ"}],"key":"CfNbTJM8kR"}],"key":"aDZp7qKDjy"},{"type":"listItem","spread":true,"position":{"start":{"line":12,"column":1},"end":{"line":12,"column":1}},"children":[{"type":"paragraph","children":[{"type":"text","value":"Either click the ","position":{"start":{"line":12,"column":1},"end":{"line":12,"column":1}},"key":"vBZGFszJ23"},{"type":"strong","position":{"start":{"line":12,"column":1},"end":{"line":12,"column":1}},"children":[{"type":"text","value":"Register","position":{"start":{"line":12,"column":1},"end":{"line":12,"column":1}},"key":"jDaEDP29s0"}],"key":"EKQoPq2wHb"},{"type":"text","value":" button and follow the instructions or use one of the alternative log in methods like GitHub","position":{"start":{"line":12,"column":1},"end":{"line":12,"column":1}},"key":"o6oECblcxr"}],"key":"japrhWsNRj"}],"key":"Ht1ec09wnF"},{"type":"listItem","spread":true,"position":{"start":{"line":13,"column":1},"end":{"line":13,"column":1}},"children":[{"type":"paragraph","children":[{"type":"text","value":"Confirm your email address following the link sent to you via email","position":{"start":{"line":13,"column":1},"end":{"line":13,"column":1}},"key":"a4aXPvs9dZ"}],"key":"aTi4HIBOcL"}],"key":"DpqfRD8l7p"},{"type":"listItem","spread":true,"position":{"start":{"line":14,"column":1},"end":{"line":14,"column":1}},"children":[{"type":"paragraph","children":[{"type":"text","value":"Agree to the terms and conditions","position":{"start":{"line":14,"column":1},"end":{"line":14,"column":1}},"key":"dKNuTnkSRs"}],"key":"q5EWEW31hr"}],"key":"CcayVm45fp"},{"type":"listItem","spread":true,"position":{"start":{"line":15,"column":1},"end":{"line":16,"column":1}},"children":[{"type":"paragraph","children":[{"type":"text","value":"Wait for the confirmation by your workspace manager","position":{"start":{"line":15,"column":1},"end":{"line":15,"column":1}},"key":"cKSUgPlUN8"}],"key":"y852TjXerC"}],"key":"swk599Etss"}],"key":"Zru1jXpwS7"},{"type":"paragraph","position":{"start":{"line":17,"column":1},"end":{"line":17,"column":1}},"children":[{"type":"text","value":"For more detailed instructions, including screenshots, see our tutorial ","position":{"start":{"line":17,"column":1},"end":{"line":17,"column":1}},"key":"BqQ7uwYx3D"},{"type":"link","url":"/creating-account","position":{"start":{"line":17,"column":1},"end":{"line":17,"column":1}},"children":[{"type":"strong","position":{"start":{"line":17,"column":1},"end":{"line":17,"column":1}},"children":[{"type":"text","value":"How to create an account in EOxHub workspaces","position":{"start":{"line":17,"column":1},"end":{"line":17,"column":1}},"key":"hFNVZ4kMOJ"}],"key":"WdACJ07B6I"}],"urlSource":"../tutorials/creating_account.md","dataUrl":"/creating-account.json","internal":true,"protocol":"file","key":"J0rlx7Q7O9"},{"type":"text","value":".","position":{"start":{"line":17,"column":1},"end":{"line":17,"column":1}},"key":"SaMmI9g1wZ"}],"key":"cBJFsgjkN0"},{"type":"heading","depth":2,"position":{"start":{"line":19,"column":1},"end":{"line":19,"column":1}},"children":[{"type":"text","value":"Log In","position":{"start":{"line":19,"column":1},"end":{"line":19,"column":1}},"key":"DGbTZlzy3C"}],"identifier":"log-in","label":"Log In","html_id":"log-in","implicit":true,"key":"ofj98IuJiq"},{"type":"paragraph","position":{"start":{"line":21,"column":1},"end":{"line":21,"column":1}},"children":[{"type":"text","value":"After your account has been approved, you can log in anytime.","position":{"start":{"line":21,"column":1},"end":{"line":21,"column":1}},"key":"rAYAW8nVyC"}],"key":"ftk9Z8veoi"},{"type":"list","ordered":true,"start":1,"spread":false,"position":{"start":{"line":23,"column":1},"end":{"line":25,"column":1}},"children":[{"type":"listItem","spread":true,"position":{"start":{"line":23,"column":1},"end":{"line":23,"column":1}},"children":[{"type":"paragraph","children":[{"type":"text","value":"Navigate to the URL of your workspace","position":{"start":{"line":23,"column":1},"end":{"line":23,"column":1}},"key":"CYdJUCQzpB"}],"key":"veE0IMDJr6"}],"key":"w6EamhWas7"},{"type":"listItem","spread":true,"position":{"start":{"line":24,"column":1},"end":{"line":25,"column":1}},"children":[{"type":"paragraph","children":[{"type":"text","value":"Either use your email address and password and click ","position":{"start":{"line":24,"column":1},"end":{"line":24,"column":1}},"key":"cRcn41mU8l"},{"type":"strong","position":{"start":{"line":24,"column":1},"end":{"line":24,"column":1}},"children":[{"type":"text","value":"Sign In","position":{"start":{"line":24,"column":1},"end":{"line":24,"column":1}},"key":"HxWoQ2gHOL"}],"key":"YzgsTwUbZZ"},{"type":"text","value":" or use one of the alternative log in methods like GitHub","position":{"start":{"line":24,"column":1},"end":{"line":24,"column":1}},"key":"SWZAPmH6uU"}],"key":"rkc0Fu2vGb"}],"key":"UuGddmTNau"}],"key":"lxEXwqAYuQ"},{"type":"heading","depth":2,"position":{"start":{"line":26,"column":1},"end":{"line":26,"column":1}},"children":[{"type":"text","value":"Navigating the user area","position":{"start":{"line":26,"column":1},"end":{"line":26,"column":1}},"key":"ygwTMCuRem"}],"identifier":"navigating-the-user-area","label":"Navigating the user area","html_id":"navigating-the-user-area","implicit":true,"key":"qIUkXCxz7s"},{"type":"paragraph","position":{"start":{"line":28,"column":1},"end":{"line":28,"column":1}},"children":[{"type":"text","value":"After signing in, you’ll see the user area with the tools available to your selected workspace. The list of actually available tools depends on the concrete workspace configuration. Their respective documentations can be found in the ","position":{"start":{"line":28,"column":1},"end":{"line":28,"column":1}},"key":"TQgcwzaxvh"},{"type":"link","url":"/jupyterlab","position":{"start":{"line":28,"column":1},"end":{"line":28,"column":1}},"children":[{"type":"text","value":"second chapter of this documentation","position":{"start":{"line":28,"column":1},"end":{"line":28,"column":1}},"key":"hxuTMN9mCT"}],"urlSource":"../applications/jupyterlab.md","dataUrl":"/jupyterlab.json","internal":true,"protocol":"file","key":"KaIm683EqL"},{"type":"text","value":".","position":{"start":{"line":28,"column":1},"end":{"line":28,"column":1}},"key":"kX7Vb9ViRP"}],"key":"OgVpS5IDk8"},{"type":"image","url":"https://documentation.hub.eox.at//build/user_area-37d54bdce89943d00406bb03d1dfc070.png","alt":"user area","position":{"start":{"line":30,"column":1},"end":{"line":30,"column":1}},"key":"eRnF8EhK2F","urlSource":"assets/user_area.png"}],"key":"APDBJDv12S"}],"key":"TzuozVwYLe"},"references":{"cite":{"order":[],"data":{}}},"footer":{"navigation":{"prev":{"title":"What is EOxHub","url":"/intro","group":"Introduction"},"next":{"title":"Frequently asked questions","url":"/faq","group":"Introduction"}}},"domain":"http://localhost:3000"}